amk/pytb/__init__.py
amk/pytb/arg_parse.py
amk/pytb/consts.py
amk/pytb/logger.py
amk/pytb/pip_package.py
amk.pytb-1.0.1.dist-info/LICENSE
amk.pytb-1.0.1.dist-info/METADATA
amk.pytb-1.0.1.dist-info/WHEEL
amk.pytb-1.0.1.dist-info/entry_points.txt
amk.pytb-1.0.1.dist-info/top_level.txt
amk.pytb-1.0.1.dist-info/RECORD
