Metadata-Version: 2.1
Name: amk.pytb
Version: 1.0.1
Summary: Python toolbox
Home-page: https://github.com/AndyM129/python_toolbox
Author: Andy Meng
Author-email: andy_m129@163.com
License: GNU General Public License v3.0
Platform: UNKNOWN
Requires-Python: >=3.9
License-File: LICENSE
Requires-Dist: colorama
